{
  "qInfo": {
    "qId": "2a5691aa-7a9d-440d-ab2f-8a38c8a15cb7",
    "qType": "appprops"
  },
  "qMetaDef": {},
  "sheetTitleBgColor": {
    "color": "#D3D8D9",
    "index": -1
  },
  "sheetTitleGradientColor": {
    "color": "#D3D8D9",
    "index": -1
  },
  "sheetTitleColor": "#595959",
  "sheetLogoThumbnail": {
    "qStaticContentUrlDef": {
      "qUrl": "/api/v1/apps/<appId>/media/files/Qlik Logo No Trademark 2 Color Positive RGB.png"
    }
  },
  "sheetLogoPosition": "",
  "rtl": false,
  "theme": "sense",
  "disableCellNavMenu": false,
  "defaultBookmarkId": null,
  "presets": [
    {
      "id": "default"
    },
    {
      "name": "Presets.Untitled",
      "id": "XZFxB",
      "navigationBar": {
        "components": {
          "logo": {
            "show": true,
            "placement": "left"
          },
          "tabsManagerAdvanced": {
            "show": true,
            "placement": "left"
          },
          "appTitle": {
            "show": true,
            "placement": "center"
          },
          "insightAdvisor": {
            "show": true,
            "placement": "right"
          },
          "notificationMenu": {
            "show": true,
            "placement": "right"
          },
          "appSwitcher": {
            "show": true,
            "placement": "right"
          },
          "profile": {
            "show": true,
            "placement": "right"
          }
        }
      },
      "toolbar": {
        "show": true,
        "components": {
          "assets": {
            "show": true,
            "placement": "left"
          },
          "selections": {
            "show": true,
            "placement": "left"
          }
        }
      },
      "sheetHeader": {
        "show": false,
        "components": {
          "sheetTitle": {
            "show": true,
            "placement": "left"
          }
        }
      }
    }
  ],
  "activePreset": "XZFxB"
}